drf_cache/__init__.py
drf_cache/apps.py
drf_cache/cache_helper.py
drf_cache/cache_key.py
drf_cache/decorators.py
drf_cache/key_builder.py
drf_cache/redis_connection.py
drf_cache/seed.py
drf_cache/singleton.py
drf_cache/utils.py
drf_cache-1.0.3.dist-info/LICENSES
drf_cache-1.0.3.dist-info/METADATA
drf_cache-1.0.3.dist-info/WHEEL
drf_cache-1.0.3.dist-info/top_level.txt
drf_cache-1.0.3.dist-info/RECORD
